LICENSE.txt
MANIFEST.in
README
README.md
setup.py
examples/hello.py
images/lppro_colorcodes.png
launchpad_rtmidi_py/__init__.py
launchpad_rtmidi_py/charset.py
launchpad_rtmidi_py/launchpad_rtmidi.py
launchpad_rtmidi_py.egg-info/PKG-INFO
launchpad_rtmidi_py.egg-info/SOURCES.txt
launchpad_rtmidi_py.egg-info/dependency_links.txt
launchpad_rtmidi_py.egg-info/requires.txt
launchpad_rtmidi_py.egg-info/top_level.txt