Metadata-Version: 1.0
Name: launchpad-rtmidi-py
Version: 0.7.0
Summary: A Novation Launchpad control suite for Python ('python-rtmidi' fork of FMMT666 package)
Home-page: https://github.com/dhilowitz/launchpad_rtmidi.py
Author: Dave Hilowitz
Author-email: dhilowitz@users.noreply.github.com
License: CC BY 4.0
Keywords: novation launchpad midi rtmidi
Platform: UNKNOWN
